inji/__init__.py
inji/ansible.py
inji/cli.py
inji/engine.py
inji/filters.py
inji/globals.py
inji/tests.py
inji/utils.py
inji-0.5.2.data/scripts/inji
inji-0.5.2.dist-info/LICENSE-2.0.txt
inji-0.5.2.dist-info/METADATA
inji-0.5.2.dist-info/WHEEL
inji-0.5.2.dist-info/top_level.txt
inji-0.5.2.dist-info/RECORD
