Metadata-Version: 2.1
Name: inji
Version: 0.5.2
Summary: Render parametrized Jinja2 templates at the CLI
Home-page: https://github.com/shalomb/inji
Author: Shalom Bhooshi
Author-email: s.bhooshi@gmail.com
License: Apache License 2.0
Download-URL: https://github.com/shalomb/inji/tarball/0.5.2
Keywords: jinja,jinja2,templating
Platform: UNKNOWN
Classifier: Development Status :: 4 - Beta
Classifier: Environment :: Console
Classifier: Intended Audience :: Developers
Classifier: Intended Audience :: System Administrators
Classifier: License :: OSI Approved :: Apache Software License
Classifier: Operating System :: OS Independent
Classifier: Programming Language :: Python :: 3
Classifier: Topic :: Software Development
Classifier: Topic :: System :: Systems Administration
Requires-Python: >=3.5
Requires-Dist: jinja2 (==2.11.*)
Requires-Dist: markdown (==3.2.*)
Requires-Dist: more-itertools
Requires-Dist: python-tr
Requires-Dist: pyyaml (==5.4.*)
Requires-Dist: requests (>=2.24)
